xperimental_data_conv/__init__.py
xperimental_data_conv/main.py
xperimental_data_conv-1.0.5.dist-info/METADATA
xperimental_data_conv-1.0.5.dist-info/WHEEL
xperimental_data_conv-1.0.5.dist-info/top_level.txt
xperimental_data_conv-1.0.5.dist-info/RECORD
